declaratives/__init__.py
declaratives/admin.py
declaratives/apps.py
declaratives/models.py
declaratives/tests.py
declaratives/urls.py
declaratives/views.py
declaratives/management/__init__.py
declaratives/management/commands/__init__.py
declaratives/management/commands/create_sample_data.py
declaratives/management/commands/populate_sample_data.py
declaratives/migrations/0001_initial.py
declaratives/migrations/0002_systemperformance_activityfeed_dragdropitem_and_more.py
declaratives/migrations/__init__.py
htmx_core/__init__.py
htmx_core/apps.py
htmx_core/initializer.py
htmx_core/dispatchers/__init__.py
htmx_core/dispatchers/htmx_dispatcher.py
htmx_core/dispatchers/htmx_mapping.py
htmx_core/middleware/__init__.py
htmx_core/middleware/htmx_benchmark_security.py
htmx_core/middleware/htmx_security.py
htmx_core/middleware/htmx_switcher.py
htmx_core/middleware/htmx_url_security.py
htmx_core/mixins/__init__.py
htmx_core/mixins/htmx_mixin.py
htmx_core/mixins/htmx_xtabs_mixins.py
htmx_core/templatetags/__init__.py
htmx_core/templatetags/htmx_tags.py
htmx_core/testkits/__init__.py
htmx_core/testkits/conftest.py
htmx_core/testkits/test_analysis_kit.py
htmx_core/testkits/test_auto_aware.py
htmx_core/testkits/test_auto_test_runner.py
htmx_core/testkits/test_base_testkit.py
htmx_core/testkits/test_config.py
htmx_core/testkits/test_content_updated.py
htmx_core/testkits/test_dashboard_integration.py
htmx_core/testkits/test_dashboard_views.py
htmx_core/testkits/test_debug_helper.py
htmx_core/testkits/test_detect_orphaned_files.py
htmx_core/testkits/test_discovery_kit.py
htmx_core/testkits/test_headers.py
htmx_core/testkits/test_htmx_core_analysis.py
htmx_core/testkits/test_htmx_core_discovery.py
htmx_core/testkits/test_init_htmx_core.py
htmx_core/testkits/test_interactions.py
htmx_core/testkits/test_loading_and_error.py
htmx_core/testkits/test_orphaned_files_kit.py
htmx_core/testkits/test_reporter.py
htmx_core/testkits/test_responses.py
htmx_core/testkits/test_run_auto_tests.py
hyperx_htmx-3.3.0.dist-info/METADATA
hyperx_htmx-3.3.0.dist-info/WHEEL
hyperx_htmx-3.3.0.dist-info/entry_points.txt
hyperx_htmx-3.3.0.dist-info/top_level.txt
hyperx_htmx-3.3.0.dist-info/RECORD
